floydipsum/__init__.py
floydipsum/__main__.py
floydipsum-1.0.0.dist-info/METADATA
floydipsum-1.0.0.dist-info/WHEEL
floydipsum-1.0.0.dist-info/entry_points.txt
floydipsum-1.0.0.dist-info/licenses/LICENSE
floydipsum-1.0.0.dist-info/RECORD
