Metadata-Version: 2.4
Name: floydipsum
Version: 1.0.0
Summary: Generates Lorem Ipsum text using Pink Floyd lyrics
License-Expression: MIT
License-File: LICENSE
Keywords: lorem,ipsum,text,generator,floyd,pink,lyrics,utility,command-line,cli
Author: Steve Scholnick
Author-email: scholnicks@gmail.com
Requires-Python: >=3.13
Classifier: Development Status :: 5 - Production/Stable
Classifier: Intended Audience :: Developers
Classifier: Programming Language :: Python :: 3.13
Classifier: License :: OSI Approved :: MIT License
Classifier: Topic :: Utilities
Requires-Dist: docopt-ng (>=0.9.0,<0.10.0)
Requires-Dist: lyricsgenius (>=3.7.2,<4.0.0)
Project-URL: Homepage, https://pypi.org/project/floydipsum/
Project-URL: Issues, https://github.com/scholnicks/floydipsum/issues
Project-URL: Repository, https://github.com/scholnicks/floydipsum/
